anyioutils/__init__.py
anyioutils/_event.py
anyioutils/_exceptions.py
anyioutils/_future.py
anyioutils/_guest.py
anyioutils/_monitor.py
anyioutils/_queue.py
anyioutils/_resource_lock.py
anyioutils/_task.py
anyioutils/_task_group.py
anyioutils/_wait.py
anyioutils/py.typed
anyioutils-0.7.4.dist-info/METADATA
anyioutils-0.7.4.dist-info/WHEEL
anyioutils-0.7.4.dist-info/licenses/LICENSE.txt
anyioutils-0.7.4.dist-info/RECORD
