Metadata-Version: 2.4
Name: anyioutils
Version: 0.7.4
Summary: Utility classes and functions for AnyIO
Project-URL: Repository, https://github.com/davidbrochart/anyioutils.git
Author-email: David Brochart <david.brochart@gmail.com>
License: Copyright (c) 2024 David Brochart
License-File: LICENSE.txt
Keywords: asyncio,trio
Classifier: Development Status :: 4 - Beta
Classifier: Programming Language :: Python
Requires-Python: >=3.9
Requires-Dist: anyio<5.0.0,>=4.8.0
Requires-Dist: exceptiongroup; python_version < '3.11'
Requires-Dist: outcome<2.0.0,>=1.3.0
Requires-Dist: typing-extensions; python_version < '3.10'
